pykwalify/__init__.py
pykwalify/cli.py
pykwalify/compat.py
pykwalify/core.py
pykwalify/errors.py
pykwalify/rule.py
pykwalify/types.py
pykwalify-1.7.0.dist-info/DESCRIPTION.rst
pykwalify-1.7.0.dist-info/LICENSE.txt
pykwalify-1.7.0.dist-info/METADATA
pykwalify-1.7.0.dist-info/RECORD
pykwalify-1.7.0.dist-info/WHEEL
pykwalify-1.7.0.dist-info/entry_points.txt
pykwalify-1.7.0.dist-info/metadata.json
pykwalify-1.7.0.dist-info/top_level.txt
