Metadata-Version: 2.1
Name: pykwalify
Version: 1.7.0
Summary: Python lib/cli for JSON/YAML schema validation
Home-page: http://github.com/grokzen/pykwalify
Author: Johan Andersson
Author-email: Grokzen@gmail.com
Maintainer: Johan Andersson
Maintainer-email: Grokzen@gmail.com
License: MIT
Platform: UNKNOWN
Classifier: Development Status :: 5 - Production/Stable
Classifier: Intended Audience :: Developers
Classifier: Operating System :: OS Independent
Classifier: License :: OSI Approved :: MIT License
Classifier: Environment :: Console
Classifier: Programming Language :: Python
Classifier: Programming Language :: Python :: 2.7
Classifier: Programming Language :: Python :: 3
Classifier: Programming Language :: Python :: 3.5
Classifier: Programming Language :: Python :: 3.6
Classifier: Programming Language :: Python :: 3.7
Provides-Extra: ruamel
